README.rst
setup.py
examples/__init__.py
examples/account/__init__.py
examples/account/app.py
examples/account/handlers.py
examples/account/models.py
examples/account/user_account_service.py
examples/chat/__init__.py
examples/chat/app.py
examples/chat/handlers.py
examples/email/__init__.py
examples/email/app.py
examples/es/__init__.py
examples/es/app.py
examples/es/handlers.py
examples/helloworld/__init__.py
examples/helloworld/app.py
examples/log/__init__.py
examples/log/app.py
examples/memcache/__init__.py
examples/memcache/app.py
examples/mongo/__init__.py
examples/mongo/app.py
examples/mongo/handlers.py
examples/mongo/models.py
examples/mongo/user_account_service.py
examples/restful/__init__.py
examples/restful/app.py
examples/restful/handlers.py
examples/taskmgr/__init__.py
examples/taskmgr/app.py
examples/taskmgr/executer.py
torstack/__init__.py
torstack/exception.py
torstack/server.py
torstack.egg-info/PKG-INFO
torstack.egg-info/SOURCES.txt
torstack.egg-info/dependency_links.txt
torstack.egg-info/not-zip-safe
torstack.egg-info/requires.txt
torstack.egg-info/top_level.txt
torstack/app/__init__.py
torstack/app/web.py
torstack/config/__init__.py
torstack/config/builder.py
torstack/config/default.py
torstack/config/parser.py
torstack/core/__init__.py
torstack/core/cookie.py
torstack/core/log.py
torstack/core/rest.py
torstack/core/scheduler.py
torstack/core/session.py
torstack/handler/__init__.py
torstack/handler/base.py
torstack/handler/mobrest.py
torstack/handler/scheduler.py
torstack/handler/webrest.py
torstack/handler/websocket.py
torstack/library/__init__.py
torstack/library/compat.py
torstack/library/dict.py
torstack/library/encipher.py
torstack/library/mediatypes.py
torstack/library/obj.py
torstack/library/string.py
torstack/library/types.py
torstack/library/utils.py
torstack/scheduler/__init__.py
torstack/scheduler/executer.py
torstack/scheduler/handler.py
torstack/scheduler/model.py
torstack/scheduler/service.py
torstack/smtp/__init__.py
torstack/smtp/email.py
torstack/smtp/listener.py
torstack/smtp/manager.py
torstack/storage/__init__.py
torstack/storage/async_file.py
torstack/storage/async_mongodb.py
torstack/storage/async_mysql.py
