Metadata-Version: 1.2
Name: torstack
Version: 0.1.1
Summary: Torstack is a bundle for Tornado. it is designed to make getting started quick and easy, so you can focus on writing your app without needing to reinvent the wheel.
Home-page: https://github.com/longniao/torstack
Author: Longniao
Author-email: longniao@gmail.com
Maintainer: Longniao
Maintainer-email: longniao@gmail.com
License: MIT
Keywords: tornado torstack
Platform: any
Classifier: Development Status :: 5 - Production/Stable
Classifier: Environment :: Console
Classifier: Intended Audience :: Developers
Classifier: License :: OSI Approved :: MIT License
Classifier: Operating System :: OS Independent
Classifier: Programming Language :: Python
Classifier: Programming Language :: Python :: 3.5
Classifier: Programming Language :: Python :: 3.6
Classifier: Programming Language :: Python :: 3.7
Requires-Python: >=3.5
